zeblok/__init__.py
zeblok/api.py
zeblok/chat.py
zeblok/client.py
zeblok/error.py
zeblok/models.py
zeblok/version.py
zeblok/base/__init__.py
zeblok/base/model.py
zeblok/utils/__init__.py
zeblok/utils/constants.py
zeblok/utils/credentials.py
zeblok_ai-1.0.0.dist-info/METADATA
zeblok_ai-1.0.0.dist-info/WHEEL
zeblok_ai-1.0.0.dist-info/top_level.txt
zeblok_ai-1.0.0.dist-info/RECORD
