Metadata-Version: 2.1
Name: zeblok-ai
Version: 1.0.0
Summary: Zeblok AI SDK for accessing pretrained models
Home-page: https://github.com/zeblok/zeblok-ai-sdk
Author: Avinash
Author-email: avinash.sampath@zeblok.com
Classifier: Programming Language :: Python :: 3
Classifier: License :: OSI Approved :: MIT License
Classifier: Operating System :: OS Independent
Requires-Python: >=3.7
Requires-Dist: requests >=2.25.1
Requires-Dist: zeblok-sdk
Provides-Extra: async
Requires-Dist: aiohttp >=3.7.4 ; extra == 'async'
Provides-Extra: dev
Requires-Dist: pytest >=6.0 ; extra == 'dev'
Requires-Dist: wheel >=0.36.2 ; extra == 'dev'
Requires-Dist: twine >=3.4.1 ; extra == 'dev'
